README.md
pyproject.toml
setup.cfg
setup.py
fourth_dimension/__init__.py
fourth_dimension/main.py
fourth_dimension.egg-info/PKG-INFO
fourth_dimension.egg-info/SOURCES.txt
fourth_dimension.egg-info/dependency_links.txt
fourth_dimension.egg-info/top_level.txt
fourth_dimension/cache/faiss_cache/temp.index
fourth_dimension/config/__init__.py
fourth_dimension/config/config.py
fourth_dimension/config/question_regex.txt
fourth_dimension/es/__init__.py
fourth_dimension/es/es_client.py
fourth_dimension/es/es_sort.py
fourth_dimension/faiss_process/__init__.py
fourth_dimension/faiss_process/faiss_index.py
fourth_dimension/faiss_process/faiss_storage.py
fourth_dimension/model/__init__.py
fourth_dimension/model/chatGPT.py
fourth_dimension/model/get_embedding_bge.py
fourth_dimension/model/model_init.py
fourth_dimension/parser/__init__.py
fourth_dimension/parser/common.py
fourth_dimension/parser/docx_parser.py
fourth_dimension/parser/files.py
fourth_dimension/utils/__init__.py
fourth_dimension/utils/embddings.py
fourth_dimension/utils/file.py
fourth_dimension/utils/file_parse.py
fourth_dimension/utils/mix_sort.py
fourth_dimension/utils/upload_file.py
fourth_dimension/utils/zutil.py