Metadata-Version: 2.1
Name: fourth-dimension
Version: 1.2
Summary: FourthDimension（第四维度）由华中科技大学人工智能与嵌入式实验室联合言图科技研发，是一款基于大语言模型的智能知识问答系统，提供私域知识库、文档问答等多种服务。此外，FourthDimension提供便捷的本地部署方法，方便用户在本地环境中搭建属于自己的应用平台。
Home-page: https://gitee.com/hustai/Fourth-Dimension
Author: yantu-tech
Author-email: GuoHuai Wu <wu466687121@qq.com>
License: MIT License
Keywords: python,yantu
Classifier: Intended Audience :: Developers
Classifier: Programming Language :: Python :: 3
Requires-Python: >=3.8
